{
  "indexes": [
    {
      "collectionGroup": "projects",
      "queryScope": "COLLECTION",
      "fields": [
        {
          "fieldPath": "createdAt",
          "order": "DESCENDING"
        },
        {
          "fieldPath": "title",
          "order": "ASCENDING"
        }
      ]
    },
    {
      "collectionGroup": "messages",
      "queryScope": "COLLECTION",
      "fields": [
        {
          "fieldPath": "createdAt",
          "order": "DESCENDING"
        },
        {
          "fieldPath": "read",
          "order": "ASCENDING"
        }
      ]
    }
  ],
  "fieldOverrides": []
} 